setup.cfg
setup.py
django_pg_utils.egg-info/PKG-INFO
django_pg_utils.egg-info/SOURCES.txt
django_pg_utils.egg-info/dependency_links.txt
django_pg_utils.egg-info/top_level.txt
pg_utils/__init__.py
pg_utils/utils.py