Metadata-Version: 1.1
Name: django-pg-utils
Version: 0.1.4
Summary: Utility methods for Django + PostgreSQL applications
Home-page: https://github.com/hypertrack/django-pg-utils
Author: HyperTrack
Author-email: devops@hypertrack.io
License: MIT
Download-URL: https://github.com/hypertrack/django-pg-utils/tarball/0.1
Keywords: orm,postgres,django
Platform: UNKNOWN
